django_object_hooks-1.2.0.dist-info/DESCRIPTION.rst
django_object_hooks-1.2.0.dist-info/METADATA
django_object_hooks-1.2.0.dist-info/metadata.json
django_object_hooks-1.2.0.dist-info/RECORD
django_object_hooks-1.2.0.dist-info/top_level.txt
django_object_hooks-1.2.0.dist-info/WHEEL
doh/__init__.py
doh/apps.py
doh/managers.py
doh/models.py
doh/signals.py
doh/tests.py
doh/deliverers/__init__.py
doh/deliverers/base.py
doh/deliverers/gevent.py
doh/deliverers/mixins.py
doh/migrations/0001_initial.py
doh/migrations/__init__.py
