Metadata-Version: 2.0
Name: django-object-hooks
Version: 1.2.0
Summary: Object-level Web Hook application
Home-page: https://github.com/laginha/django-object-hooks
Author: Diogo Laginha
Author-email: diogo.laginha.machado@gmail.com
License: MIT
Platform: UNKNOWN
Classifier: License :: OSI Approved :: MIT License
Classifier: Programming Language :: Python :: 2
Classifier: Intended Audience :: Developers
Requires-Dist: django
Requires-Dist: celery
Requires-Dist: requests
Requires-Dist: grequests
Requires-Dist: ujson
